tinycom/__init__.py
tinycom/__main__.py
tinycom/guisave.py
tinycom/pyside_dynamic.py
tinycom/qt.py
tinycom/serialthread.py
tinycom/settings.ui
tinycom/tinycom.py
tinycom/tinycom.ui
tinycom/tinycom_rc.py
tinycom/res/tinycom.qrc
tinycom/res/32x32/tinycom.png
tinycom-1.1.dist-info/DESCRIPTION.rst
tinycom-1.1.dist-info/METADATA
tinycom-1.1.dist-info/RECORD
tinycom-1.1.dist-info/WHEEL
tinycom-1.1.dist-info/entry_points.txt
tinycom-1.1.dist-info/metadata.json
tinycom-1.1.dist-info/top_level.txt
