Metadata-Version: 2.0
Name: tinycom
Version: 1.1
Summary: A simple line based serial terminal GUI.
Home-page: https://github.com/digitalpeer/tinycom
Author: Joshua Henderson
Author-email: digitalpeer@digitalpeer.com
License: GPL3
Download-URL: https://github.com/digitalpeer/tinycom/zipball/master
Keywords: serial terminal
Platform: UNKNOWN
Classifier: Development Status :: 3 - Alpha
Classifier: Natural Language :: English
Classifier: Operating System :: OS Independent
Classifier: Programming Language :: Python :: 2
Classifier: Programming Language :: Python :: 2.7
Classifier: Programming Language :: Python :: 3
Classifier: Programming Language :: Python :: 3.5
Classifier: License :: OSI Approved :: GNU General Public License v3 (GPLv3)
Classifier: Topic :: Terminals :: Serial
Classifier: Intended Audience :: End Users/Desktop
Classifier: Intended Audience :: Developers
Classifier: Intended Audience :: Information Technology
